{
  "Luterra": {
    "Luterra": 0,
    "Tortoyk": 1100,
    "Anikka": 2000,
    "Arthetine": 3400,
    "Shushire": 5000,
    "NorthVern": 2100,
    "Rohendel": 7100,
    "Feiton": 11000,
    "Yorn": 10000,
    "Punika": 7600,
    "SouthVern": 5500,
    "Pleccia": 3200,
    "Rowen": 9600,
    "Voldis": 7900,
    "Kurzan": 6000
  },
  "Tortoyk": {
    "Luterra": 1100,
    "Tortoyk": 0,
    "Anikka": 1100,
    "Arthetine": 2500,
    "Shushire": 4600,
    "NorthVern": 1900,
    "Rohendel": 8000,
    "Feiton": 12000,
    "Yorn": 12000,
    "Punika": 9300,
    "SouthVern": 6100,
    "Pleccia": 2200,
    "Rowen": 9300,
    "Voldis": 9900,
    "Kurzan": 4200
  },
  "Anikka": {
    "Luterra": 2000,
    "Tortoyk": 1100,
    "Anikka": 0,
    "Arthetine": 1600,
    "Shushire": 4200,
    "NorthVern": 2000,
    "Rohendel": 8800,
    "Feiton": 13000,
    "Yorn": 13000,
    "Punika": 11000,
    "SouthVern": 6900,
    "Pleccia": 1700,
    "Rowen": 8900,
    "Voldis": 12000,
    "Kurzan": 2700
  },
  "Arthetine": {
    "Luterra": 3400,
    "Tortoyk": 2500,
    "Anikka": 1600,
    "Arthetine": 0,
    "Shushire": 2900,
    "NorthVern": 2100,
    "Rohendel": 8900,
    "Feiton": 12000,
    "Yorn": 14000,
    "Punika": 12000,
    "SouthVern": 7000,
    "Pleccia": 2400,
    "Rowen": 7000,
    "Voldis": 14000,
    "Kurzan": 2500
  },
  "Shushire": {
    "Luterra": 5000,
    "Tortoyk": 4600,
    "Anikka": 4200,
    "Arthetine": 2900,
    "Shushire": 0,
    "NorthVern": 2600,
    "Rohendel": 6000,
    "Feiton": 6800,
    "Yorn": 11000,
    "Punika": 10000,
    "SouthVern": 4800,
    "Pleccia": 5200,
    "Rowen": 2100,
    "Voldis": 13000,
    "Kurzan": 7600
  },
  "NorthVern": {
    "Luterra": 2100,
    "Tortoyk": 1900,
    "Anikka": 2000,
    "Arthetine": 2100,
    "Shushire": 2600,
    "NorthVern": 0,
    "Rohendel": 5700,
    "Feiton": 8400,
    "Yorn": 9500,
    "Punika": 7600,
    "SouthVern": 3000,
    "Pleccia": 1900,
    "Rowen": 5600,
    "Voldis": 9000,
    "Kurzan": 5400
  },
  "Rohendel": {
    "Luterra": 8600,
    "Tortoyk": 9700,
    "Anikka": 11000,
    "Arthetine": 11000,
    "Shushire": 7300,
    "NorthVern": 7000,
    "Rohendel": 0,
    "Feiton": 4100,
    "Yorn": 4400,
    "Punika": 4900,
    "SouthVern": 5500,
    "Pleccia": 14000,
    "Rowen": 9700,
    "Voldis": 8000,
    "Kurzan": 22000
  },
  "Feiton": {
    "Luterra": 17000,
    "Tortoyk": 18000,
    "Anikka": 19000,
    "Arthetine": 18000,
    "Shushire": 10000,
    "NorthVern": 13000,
    "Rohendel": 5200,
    "Feiton": 0,
    "Yorn": 12000,
    "Punika": 15000,
    "SouthVern": 12000,
    "Pleccia": 26000,
    "Rowen": 12000,
    "Voldis": 21000,
    "Kurzan": 37000
  },
  "Yorn": {
    "Luterra": 13000,
    "Tortoyk": 15000,
    "Anikka": 17000,
    "Arthetine": 18000,
    "Shushire": 14000,
    "NorthVern": 13000,
    "Rohendel": 4900,
    "Feiton": 10000,
    "Yorn": 0,
    "Punika": 6100,
    "SouthVern": 13000,
    "Pleccia": 25000,
    "Rowen": 20000,
    "Voldis": 7800,
    "Kurzan": 35000
  },
  "Punika": {
    "Luterra": 12000,
    "Tortoyk": 15000,
    "Anikka": 18000,
    "Arthetine": 20000,
    "Shushire": 17000,
    "NorthVern": 12000,
    "Rohendel": 6500,
    "Feiton": 16000,
    "Yorn": 7400,
    "Punika": 0,
    "SouthVern": 12000,
    "Pleccia": 25000,
    "Rowen": 25000,
    "Voldis": 5500,
    "Kurzan": 38000
  },
  "SouthVern": {
    "Luterra": 8900,
    "Tortoyk": 9900,
    "Anikka": 11000,
    "Arthetine": 11000,
    "Shushire": 7700,
    "NorthVern": 3000,
    "Rohendel": 7300,
    "Feiton": 13000,
    "Yorn": 16000,
    "Punika": 12000,
    "SouthVern": 0,
    "Pleccia": 14000,
    "Rowen": 12000,
    "Voldis": 17000,
    "Kurzan": 25000
  },
  "Pleccia": {
    "Luterra": 5200,
    "Tortoyk": 3500,
    "Anikka": 2800,
    "Arthetine": 3800,
    "Shushire": 8300,
    "NorthVern": 3000,
    "Rohendel": 19000,
    "Feiton": 28000,
    "Yorn": 30000,
    "Punika": 25000,
    "SouthVern": 14000,
    "Pleccia": 0,
    "Rowen": 18000,
    "Voldis": 28000,
    "Kurzan": 9400
  },
  "Rowen": {
    "Luterra": 15000,
    "Tortoyk": 15000,
    "Anikka": 14000,
    "Arthetine": 11000,
    "Shushire": 3400,
    "NorthVern": 9100,
    "Rohendel": 13000,
    "Feiton": 13000,
    "Yorn": 24000,
    "Punika": 25000,
    "SouthVern": 12000,
    "Pleccia": 18000,
    "Rowen": 0,
    "Voldis": 32000,
    "Kurzan": 26000
  },
  "Voldis": {
    "Luterra": 13000,
    "Tortoyk": 16000,
    "Anikka": 19000,
    "Arthetine": 22000,
    "Shushire": 20000,
    "NorthVern": 15000,
    "Rohendel": 11000,
    "Feiton": 22000,
    "Yorn": 9400,
    "Punika": 5500,
    "SouthVern": 17000,
    "Pleccia": 28000,
    "Rowen": 31000,
    "Voldis": 0,
    "Kurzan": 41000
  },
  "Kurzan": {
    "Luterra": 9700,
    "Tortoyk": 6900,
    "Anikka": 4300,
    "Arthetine": 4000,
    "Shushire": 12000,
    "NorthVern": 8600,
    "Rohendel": 29000,
    "Feiton": 39000,
    "Yorn": 42000,
    "Punika": 38000,
    "SouthVern": 25000,
    "Pleccia": 9400,
    "Rowen": 26000,
    "Voldis": 41000,
    "Kurzan": 0
  }
}